{
    "orders": [{
            "email": "email@sample.com",
            "items": "1",
            "name": "Sample",
            "order": "Sample Order 1",
            "phone": "0123456789",
            "price": "5",
            "total": 0,
            "date": "03/4/20",
            "uid": "1675303448945",
            "orderno": "1"
        },
        {
            "email": "email@sample.com",
            "items": "2",
            "name": "Sample",
            "order": "Sample Order 2",
            "phone": "0123456789",
            "price": "10",
            "total": 0,
            "date": "03/4/20",
            "uid": "1675303448945",
            "orderno": "2"
        },
        {
            "email": "email@sample.com",
            "items": "3",
            "name": "Sample",
            "order": "Sample Order 3",
            "phone": "0123456789",
            "price": "15",
            "total": 0,
            "date": "03/4/20",
            "uid": "1675303448945",
            "orderno": "3"
        },
        {
            "email": "email@sample.com",
            "items": "4",
            "name": "Sample",
            "order": "Sample Order 4",
            "phone": "0123456789",
            "price": "20",
            "total": 0,
            "date": "03/4/20",
            "uid": "1675303448945",
            "orderno": "4"
        },
        {
            "email": "email@sample.com",
            "items": "5",
            "name": "Sample",
            "order": "Sample Order 5",
            "phone": "0123456789",
            "price": "25",
            "total": 0,
            "date": "03/4/20",
            "uid": "1675303448945",
            "orderno": "5"
        },
        {
            "email": "email@sample.com",
            "items": "6",
            "name": "Sample",
            "order": "Sample Order 6",
            "phone": "0123456789",
            "price": "30",
            "total": 0,
            "date": "03/4/20",
            "uid": "1675303448945",
            "orderno": "6"
        },
        {
            "email": "email@sample.com",
            "items": "7",
            "name": "Sample",
            "order": "Sample Order 7",
            "phone": "0123456789",
            "price": "35",
            "total": 0,
            "date": "03/4/20",
            "uid": "1675303448945",
            "orderno": "7"
        },
        {
            "email": "email@sample.com",
            "items": "8",
            "name": "Sample",
            "order": "Sample Order 8",
            "phone": "0123456789",
            "price": "40",
            "total": 0,
            "date": "03/4/20",
            "uid": "1675303448945",
            "orderno": "8"
        },
        {
            "email": "email@sample.com",
            "items": "9",
            "name": "Sample",
            "order": "Sample Order 9",
            "phone": "0123456789",
            "price": "45",
            "total": 0,
            "date": "03/4/20",
            "uid": "1675303448945",
            "orderno": "9"
        },
        {
            "email": "email@sample.com",
            "items": "10",
            "name": "Sample",
            "order": "Sample Order 10",
            "phone": "0123456789",
            "price": "50",
            "total": 0,
            "date": "03/4/20",
            "uid": "1675303448945",
            "orderno": "10"
        },
        {
            "email": "email@sample.com",
            "items": "11",
            "name": "Sample",
            "order": "Sample Order 11",
            "phone": "0123456789",
            "price": "55",
            "total": 0,
            "date": "03/4/20",
            "uid": "1675303448945",
            "orderno": "11"
        },
        {
            "email": "email@sample.com",
            "items": "12",
            "name": "Sample",
            "order": "Sample Order 12",
            "phone": "0123456789",
            "price": "60",
            "total": 0,
            "date": "03/4/20",
            "uid": "1675303448945",
            "orderno": "12"
        },
        {
            "email": "email@sample.com",
            "items": "13",
            "name": "Sample",
            "order": "Sample Order 13",
            "phone": "0123456789",
            "price": "65",
            "total": 0,
            "date": "03/4/20",
            "uid": "1675303448945",
            "orderno": "13"
        },
        {
            "email": "email@sample.com",
            "items": "14",
            "name": "Sample",
            "order": "Sample Order 14",
            "phone": "0123456789",
            "price": "70",
            "total": 0,
            "date": "03/4/20",
            "uid": "1675303448945",
            "orderno": "14"
        },
        {
            "email": "email@sample.com",
            "items": "15",
            "name": "Sample",
            "order": "Sample Order 15",
            "phone": "0123456789",
            "price": "75",
            "total": 0,
            "date": "03/4/20",
            "uid": "1675303448945",
            "orderno": "15"
        },
        {
            "email": "email@sample.com",
            "items": "16",
            "name": "Sample",
            "order": "Sample Order 16",
            "phone": "0123456789",
            "price": "80",
            "total": 0,
            "date": "03/4/20",
            "uid": "1675303448945",
            "orderno": "16"
        },
        {
            "email": "email@sample.com",
            "items": "17",
            "name": "Sample",
            "order": "Sample Order 17",
            "phone": "0123456789",
            "price": "85",
            "total": 0,
            "date": "03/4/20",
            "uid": "1675303448945",
            "orderno": "17"
        },
        {
            "email": "email@sample.com",
            "items": "18",
            "name": "Sample",
            "order": "Sample Order 18",
            "phone": "0123456789",
            "price": "90",
            "total": 0,
            "date": "03/4/20",
            "uid": "1675303448945",
            "orderno": "18"
        },
        {
            "email": "email@sample.com",
            "items": "19",
            "name": "Sample",
            "order": "Sample Order 19",
            "phone": "0123456789",
            "price": "95",
            "total": 0,
            "date": "03/4/20",
            "uid": "1675303448945",
            "orderno": "19"
        },
        {
            "email": "email@sample.com",
            "items": "20",
            "name": "Sample",
            "order": "Sample Order 20",
            "phone": "0123456789",
            "price": "100",
            "total": 0,
            "date": "03/4/20",
            "uid": "1675303448945",
            "orderno": "20"
        },
        {
            "email": "email@sample.com",
            "items": "21",
            "name": "Sample",
            "order": "Sample Order 21",
            "phone": "0123456789",
            "price": "105",
            "total": 0,
            "date": "03/4/20",
            "uid": "1675303448945",
            "orderno": "21"
        },
        {
            "email": "email@sample.com",
            "items": "22",
            "name": "Sample",
            "order": "Sample Order 22",
            "phone": "0123456789",
            "price": "110",
            "total": 0,
            "date": "03/4/20",
            "uid": "1675303448945",
            "orderno": "22"
        },
        {
            "email": "email@sample.com",
            "items": "23",
            "name": "Sample",
            "order": "Sample Order 23",
            "phone": "0123456789",
            "price": "115",
            "total": 0,
            "date": "03/4/20",
            "uid": "1675303448945",
            "orderno": "23"
        },
        {
            "email": "email@sample.com",
            "items": "24",
            "name": "Sample",
            "order": "Sample Order 24",
            "phone": "0123456789",
            "price": "120",
            "total": 0,
            "date": "03/4/20",
            "uid": "1675303448945",
            "orderno": "24"
        },
        {
            "email": "email@sample.com",
            "items": "25",
            "name": "Sample",
            "order": "Sample Order 25",
            "phone": "0123456789",
            "price": "125",
            "total": 0,
            "date": "03/4/20",
            "uid": "1675303448945",
            "orderno": "25"
        },
        {
            "email": "email@sample.com",
            "items": "26",
            "name": "Sample",
            "order": "Sample Order 26",
            "phone": "0123456789",
            "price": "130",
            "total": 0,
            "date": "03/4/20",
            "uid": "1675303448945",
            "orderno": "26"
        },
        {
            "email": "email@sample.com",
            "items": "27",
            "name": "Sample",
            "order": "Sample Order 27",
            "phone": "0123456789",
            "price": "135",
            "total": 0,
            "date": "03/4/20",
            "uid": "1675303448945",
            "orderno": "27"
        },
        {
            "email": "email@sample.com",
            "items": "28",
            "name": "Sample",
            "order": "Sample Order 28",
            "phone": "0123456789",
            "price": "140",
            "total": 0,
            "date": "03/4/20",
            "uid": "1675303448945",
            "orderno": "28"
        },
        {
            "email": "email@sample.com",
            "items": "29",
            "name": "Sample",
            "order": "Sample Order 29",
            "phone": "0123456789",
            "price": "145",
            "total": 0,
            "date": "03/4/20",
            "uid": "1675303448945",
            "orderno": "29"
        },
        {
            "email": "email@sample.com",
            "items": "30",
            "name": "Sample",
            "order": "Sample Order 30",
            "phone": "0123456789",
            "price": "150",
            "total": 0,
            "date": "03/4/20",
            "uid": "1675303448945",
            "orderno": "30"
        },
        {
            "email": "email@sample.com",
            "items": "31",
            "name": "Sample",
            "order": "Sample Order 31",
            "phone": "0123456789",
            "price": "155",
            "total": 0,
            "date": "03/4/20",
            "uid": "1675303448945",
            "orderno": "31"
        },
        {
            "email": "email@sample.com",
            "items": "32",
            "name": "Sample",
            "order": "Sample Order 32",
            "phone": "0123456789",
            "price": "160",
            "total": 0,
            "date": "03/4/20",
            "uid": "1675303448945",
            "orderno": "32"
        },
        {
            "email": "email@sample.com",
            "items": "33",
            "name": "Sample",
            "order": "Sample Order 33",
            "phone": "0123456789",
            "price": "165",
            "total": 0,
            "date": "03/4/20",
            "uid": "1675303448945",
            "orderno": "33"
        },
        {
            "email": "email@sample.com",
            "items": "34",
            "name": "Sample",
            "order": "Sample Order 34",
            "phone": "0123456789",
            "price": "170",
            "total": 0,
            "date": "03/4/20",
            "uid": "1675303448945",
            "orderno": "34"
        },
        {
            "email": "email@sample.com",
            "items": "35",
            "name": "Sample",
            "order": "Sample Order 35",
            "phone": "0123456789",
            "price": "175",
            "total": 0,
            "date": "03/4/20",
            "uid": "1675303448945",
            "orderno": "35"
        },
        {
            "email": "email@sample.com",
            "items": "36",
            "name": "Sample",
            "order": "Sample Order 36",
            "phone": "0123456789",
            "price": "180",
            "total": 0,
            "date": "03/4/20",
            "uid": "1675303448945",
            "orderno": "36"
        },
        {
            "email": "email@sample.com",
            "items": "37",
            "name": "Sample",
            "order": "Sample Order 37",
            "phone": "0123456789",
            "price": "185",
            "total": 0,
            "date": "03/4/20",
            "uid": "1675303448945",
            "orderno": "37"
        },
        {
            "email": "email@sample.com",
            "items": "38",
            "name": "Sample",
            "order": "Sample Order 38",
            "phone": "0123456789",
            "price": "190",
            "total": 0,
            "date": "03/4/20",
            "uid": "1675303448945",
            "orderno": "38"
        },
        {
            "email": "email@sample.com",
            "items": "39",
            "name": "Sample",
            "order": "Sample Order 39",
            "phone": "0123456789",
            "price": "195",
            "total": 0,
            "date": "03/4/20",
            "uid": "1675303448945",
            "orderno": "39"
        },
        {
            "email": "email@sample.com",
            "items": "40",
            "name": "Sample",
            "order": "Sample Order 40",
            "phone": "0123456789",
            "price": "200",
            "total": 0,
            "date": "03/4/20",
            "uid": "1675303448945",
            "orderno": "40"
        },
        {
            "email": "email@sample.com",
            "items": "41",
            "name": "Sample",
            "order": "Sample Order 41",
            "phone": "0123456789",
            "price": "205",
            "total": 0,
            "date": "03/4/20",
            "uid": "1675303448945",
            "orderno": "41"
        },
        {
            "email": "email@sample.com",
            "items": "42",
            "name": "Sample",
            "order": "Sample Order 42",
            "phone": "0123456789",
            "price": "210",
            "total": 0,
            "date": "03/4/20",
            "uid": "1675303448945",
            "orderno": "42"
        },
        {
            "email": "email@sample.com",
            "items": "43",
            "name": "Sample",
            "order": "Sample Order 43",
            "phone": "0123456789",
            "price": "215",
            "total": 0,
            "date": "03/4/20",
            "uid": "1675303448945",
            "orderno": "43"
        },
        {
            "email": "email@sample.com",
            "items": "44",
            "name": "Sample",
            "order": "Sample Order 44",
            "phone": "0123456789",
            "price": "220",
            "total": 0,
            "date": "03/4/20",
            "uid": "1675303448945",
            "orderno": "44"
        },
        {
            "email": "email@sample.com",
            "items": "45",
            "name": "Sample",
            "order": "Sample Order 45",
            "phone": "0123456789",
            "price": "225",
            "total": 0,
            "date": "03/4/20",
            "uid": "1675303448945",
            "orderno": "45"
        },
        {
            "email": "email@sample.com",
            "items": "46",
            "name": "Sample",
            "order": "Sample Order 46",
            "phone": "0123456789",
            "price": "230",
            "total": 0,
            "date": "03/4/20",
            "uid": "1675303448945",
            "orderno": "46"
        },
        {
            "email": "email@sample.com",
            "items": "47",
            "name": "Sample",
            "order": "Sample Order 47",
            "phone": "0123456789",
            "price": "235",
            "total": 0,
            "date": "03/4/20",
            "uid": "1675303448945",
            "orderno": "47"
        },
        {
            "email": "email@sample.com",
            "items": "48",
            "name": "Sample",
            "order": "Sample Order 48",
            "phone": "0123456789",
            "price": "240",
            "total": 0,
            "date": "03/4/20",
            "uid": "1675303448945",
            "orderno": "48"
        },
        {
            "email": "email@sample.com",
            "items": "49",
            "name": "Sample",
            "order": "Sample Order 49",
            "phone": "0123456789",
            "price": "245",
            "total": 0,
            "date": "03/4/20",
            "uid": "1675303448945",
            "orderno": "49"
        },
        {
            "email": "email@sample.com",
            "items": "50",
            "name": "Sample",
            "order": "Sample Order 50",
            "phone": "0123456789",
            "price": "250",
            "total": 0,
            "date": "03/4/20",
            "uid": "1675303448945",
            "orderno": "50"
        },
        {
            "email": "email@sample.com",
            "items": "51",
            "name": "Sample",
            "order": "Sample Order 51",
            "phone": "0123456789",
            "price": "255",
            "total": 0,
            "date": "03/4/20",
            "uid": "1675303448945",
            "orderno": "51"
        },
        {
            "email": "email@sample.com",
            "items": "52",
            "name": "Sample",
            "order": "Sample Order 52",
            "phone": "0123456789",
            "price": "260",
            "total": 0,
            "date": "03/4/20",
            "uid": "1675303448945",
            "orderno": "52"
        },
        {
            "email": "email@sample.com",
            "items": "53",
            "name": "Sample",
            "order": "Sample Order 53",
            "phone": "0123456789",
            "price": "265",
            "total": 0,
            "date": "03/4/20",
            "uid": "1675303448945",
            "orderno": "53"
        },
        {
            "email": "email@sample.com",
            "items": "54",
            "name": "Sample",
            "order": "Sample Order 54",
            "phone": "0123456789",
            "price": "270",
            "total": 0,
            "date": "03/4/20",
            "uid": "1675303448945",
            "orderno": "54"
        },
        {
            "email": "email@sample.com",
            "items": "55",
            "name": "Sample",
            "order": "Sample Order 55",
            "phone": "0123456789",
            "price": "275",
            "total": 0,
            "date": "03/4/20",
            "uid": "1675303448945",
            "orderno": "55"
        },
        {
            "email": "email@sample.com",
            "items": "56",
            "name": "Sample",
            "order": "Sample Order 56",
            "phone": "0123456789",
            "price": "280",
            "total": 0,
            "date": "03/4/20",
            "uid": "1675303448945",
            "orderno": "56"
        },
        {
            "email": "email@sample.com",
            "items": "57",
            "name": "Sample",
            "order": "Sample Order 57",
            "phone": "0123456789",
            "price": "285",
            "total": 0,
            "date": "03/4/20",
            "uid": "1675303448945",
            "orderno": "57"
        },
        {
            "email": "email@sample.com",
            "items": "58",
            "name": "Sample",
            "order": "Sample Order 58",
            "phone": "0123456789",
            "price": "290",
            "total": 0,
            "date": "03/4/20",
            "uid": "1675303448945",
            "orderno": "58"
        },
        {
            "email": "email@sample.com",
            "items": "59",
            "name": "Sample",
            "order": "Sample Order 59",
            "phone": "0123456789",
            "price": "295",
            "total": 0,
            "date": "03/4/20",
            "uid": "1675303448945",
            "orderno": "59"
        },
        {
            "email": "email@sample.com",
            "items": "60",
            "name": "Sample",
            "order": "Sample Order 60",
            "phone": "0123456789",
            "price": "300",
            "total": 0,
            "date": "03/4/20",
            "uid": "1675303448945",
            "orderno": "60"
        },
        {
            "email": "email@sample.com",
            "items": "61",
            "name": "Sample",
            "order": "Sample Order 61",
            "phone": "0123456789",
            "price": "305",
            "total": 0,
            "date": "03/4/20",
            "uid": "1675303448945",
            "orderno": "61"
        },
        {
            "email": "email@sample.com",
            "items": "62",
            "name": "Sample",
            "order": "Sample Order 62",
            "phone": "0123456789",
            "price": "310",
            "total": 0,
            "date": "03/4/20",
            "uid": "1675303448945",
            "orderno": "62"
        },
        {
            "email": "email@sample.com",
            "items": "63",
            "name": "Sample",
            "order": "Sample Order 63",
            "phone": "0123456789",
            "price": "315",
            "total": 0,
            "date": "03/4/20",
            "uid": "1675303448945",
            "orderno": "63"
        },
        {
            "email": "email@sample.com",
            "items": "64",
            "name": "Sample",
            "order": "Sample Order 64",
            "phone": "0123456789",
            "price": "320",
            "total": 0,
            "date": "03/4/20",
            "uid": "1675303448945",
            "orderno": "64"
        },
        {
            "email": "email@sample.com",
            "items": "65",
            "name": "Sample",
            "order": "Sample Order 65",
            "phone": "0123456789",
            "price": "325",
            "total": 0,
            "date": "03/4/20",
            "uid": "1675303448945",
            "orderno": "65"
        },
        {
            "email": "email@sample.com",
            "items": "66",
            "name": "Sample",
            "order": "Sample Order 66",
            "phone": "0123456789",
            "price": "330",
            "total": 0,
            "date": "03/4/20",
            "uid": "1675303448945",
            "orderno": "66"
        },
        {
            "email": "email@sample.com",
            "items": "67",
            "name": "Sample",
            "order": "Sample Order 67",
            "phone": "0123456789",
            "price": "335",
            "total": 0,
            "date": "03/4/20",
            "uid": "1675303448945",
            "orderno": "67"
        },
        {
            "email": "email@sample.com",
            "items": "68",
            "name": "Sample",
            "order": "Sample Order 68",
            "phone": "0123456789",
            "price": "340",
            "total": 0,
            "date": "03/4/20",
            "uid": "1675303448945",
            "orderno": "68"
        },
        {
            "email": "email@sample.com",
            "items": "69",
            "name": "Sample",
            "order": "Sample Order 69",
            "phone": "0123456789",
            "price": "345",
            "total": 0,
            "date": "03/4/20",
            "uid": "1675303448945",
            "orderno": "69"
        },
        {
            "email": "email@sample.com",
            "items": "70",
            "name": "Sample",
            "order": "Sample Order 70",
            "phone": "0123456789",
            "price": "350",
            "total": 0,
            "date": "03/4/20",
            "uid": "1675303448945",
            "orderno": "70"
        },
        {
            "email": "email@sample.com",
            "items": "71",
            "name": "Sample",
            "order": "Sample Order 71",
            "phone": "0123456789",
            "price": "355",
            "total": 0,
            "date": "03/4/20",
            "uid": "1675303448945",
            "orderno": "71"
        },
        {
            "email": "email@sample.com",
            "items": "72",
            "name": "Sample",
            "order": "Sample Order 72",
            "phone": "0123456789",
            "price": "360",
            "total": 0,
            "date": "03/4/20",
            "uid": "1675303448945",
            "orderno": "72"
        },
        {
            "email": "email@sample.com",
            "items": "73",
            "name": "Sample",
            "order": "Sample Order 73",
            "phone": "0123456789",
            "price": "365",
            "total": 0,
            "date": "03/4/20",
            "uid": "1675303448945",
            "orderno": "73"
        },
        {
            "email": "email@sample.com",
            "items": "74",
            "name": "Sample",
            "order": "Sample Order 74",
            "phone": "0123456789",
            "price": "370",
            "total": 0,
            "date": "03/4/20",
            "uid": "1675303448945",
            "orderno": "74"
        },
        {
            "email": "email@sample.com",
            "items": "75",
            "name": "Sample",
            "order": "Sample Order 75",
            "phone": "0123456789",
            "price": "375",
            "total": 0,
            "date": "03/4/20",
            "uid": "1675303448945",
            "orderno": "75"
        },
        {
            "email": "email@sample.com",
            "items": "76",
            "name": "Sample",
            "order": "Sample Order 76",
            "phone": "0123456789",
            "price": "380",
            "total": 0,
            "date": "03/4/20",
            "uid": "1675303448945",
            "orderno": "76"
        },
        {
            "email": "email@sample.com",
            "items": "77",
            "name": "Sample",
            "order": "Sample Order 77",
            "phone": "0123456789",
            "price": "385",
            "total": 0,
            "date": "03/4/20",
            "uid": "1675303448945",
            "orderno": "77"
        },
        {
            "email": "email@sample.com",
            "items": "78",
            "name": "Sample",
            "order": "Sample Order 78",
            "phone": "0123456789",
            "price": "390",
            "total": 0,
            "date": "03/4/20",
            "uid": "1675303448945",
            "orderno": "78"
        },
        {
            "email": "email@sample.com",
            "items": "79",
            "name": "Sample",
            "order": "Sample Order 79",
            "phone": "0123456789",
            "price": "395",
            "total": 0,
            "date": "03/4/20",
            "uid": "1675303448945",
            "orderno": "79"
        },
        {
            "email": "email@sample.com",
            "items": "80",
            "name": "Sample",
            "order": "Sample Order 80",
            "phone": "0123456789",
            "price": "400",
            "total": 0,
            "date": "03/4/20",
            "uid": "1675303448945",
            "orderno": "80"
        },
        {
            "email": "email@sample.com",
            "items": "81",
            "name": "Sample",
            "order": "Sample Order 81",
            "phone": "0123456789",
            "price": "405",
            "total": 0,
            "date": "03/4/20",
            "uid": "1675303448945",
            "orderno": "81"
        },
        {
            "email": "email@sample.com",
            "items": "82",
            "name": "Sample",
            "order": "Sample Order 82",
            "phone": "0123456789",
            "price": "410",
            "total": 0,
            "date": "03/4/20",
            "uid": "1675303448945",
            "orderno": "82"
        },
        {
            "email": "email@sample.com",
            "items": "83",
            "name": "Sample",
            "order": "Sample Order 83",
            "phone": "0123456789",
            "price": "415",
            "total": 0,
            "date": "03/4/20",
            "uid": "1675303448945",
            "orderno": "83"
        },
        {
            "email": "email@sample.com",
            "items": "84",
            "name": "Sample",
            "order": "Sample Order 84",
            "phone": "0123456789",
            "price": "420",
            "total": 0,
            "date": "03/4/20",
            "uid": "1675303448945",
            "orderno": "84"
        },
        {
            "email": "email@sample.com",
            "items": "85",
            "name": "Sample",
            "order": "Sample Order 85",
            "phone": "0123456789",
            "price": "425",
            "total": 0,
            "date": "03/4/20",
            "uid": "1675303448945",
            "orderno": "85"
        },
        {
            "email": "email@sample.com",
            "items": "86",
            "name": "Sample",
            "order": "Sample Order 86",
            "phone": "0123456789",
            "price": "430",
            "total": 0,
            "date": "03/4/20",
            "uid": "1675303448945",
            "orderno": "86"
        },
        {
            "email": "email@sample.com",
            "items": "87",
            "name": "Sample",
            "order": "Sample Order 87",
            "phone": "0123456789",
            "price": "435",
            "total": 0,
            "date": "03/4/20",
            "uid": "1675303448945",
            "orderno": "87"
        },
        {
            "email": "email@sample.com",
            "items": "88",
            "name": "Sample",
            "order": "Sample Order 88",
            "phone": "0123456789",
            "price": "440",
            "total": 0,
            "date": "03/4/20",
            "uid": "1675303448945",
            "orderno": "88"
        },
        {
            "email": "email@sample.com",
            "items": "89",
            "name": "Sample",
            "order": "Sample Order 89",
            "phone": "0123456789",
            "price": "445",
            "total": 0,
            "date": "03/4/20",
            "uid": "1675303448945",
            "orderno": "89"
        },
        {
            "email": "email@sample.com",
            "items": "90",
            "name": "Sample",
            "order": "Sample Order 90",
            "phone": "0123456789",
            "price": "450",
            "total": 0,
            "date": "03/4/20",
            "uid": "1675303448945",
            "orderno": "90"
        },
        {
            "email": "email@sample.com",
            "items": "91",
            "name": "Sample",
            "order": "Sample Order 91",
            "phone": "0123456789",
            "price": "455",
            "total": 0,
            "date": "03/4/20",
            "uid": "1675303448945",
            "orderno": "91"
        },
        {
            "email": "email@sample.com",
            "items": "92",
            "name": "Sample",
            "order": "Sample Order 92",
            "phone": "0123456789",
            "price": "460",
            "total": 0,
            "date": "03/4/20",
            "uid": "1675303448945",
            "orderno": "92"
        },
        {
            "email": "email@sample.com",
            "items": "93",
            "name": "Sample",
            "order": "Sample Order 93",
            "phone": "0123456789",
            "price": "465",
            "total": 0,
            "date": "03/4/20",
            "uid": "1675303448945",
            "orderno": "93"
        },
        {
            "email": "email@sample.com",
            "items": "94",
            "name": "Sample",
            "order": "Sample Order 94",
            "phone": "0123456789",
            "price": "470",
            "total": 0,
            "date": "03/4/20",
            "uid": "1675303448945",
            "orderno": "94"
        },
        {
            "email": "email@sample.com",
            "items": "95",
            "name": "Sample",
            "order": "Sample Order 95",
            "phone": "0123456789",
            "price": "475",
            "total": 0,
            "date": "03/4/20",
            "uid": "1675303448945",
            "orderno": "95"
        },
        {
            "email": "email@sample.com",
            "items": "96",
            "name": "Sample",
            "order": "Sample Order 96",
            "phone": "0123456789",
            "price": "480",
            "total": 0,
            "date": "03/4/20",
            "uid": "1675303448945",
            "orderno": "96"
        },
        {
            "email": "email@sample.com",
            "items": "97",
            "name": "Sample",
            "order": "Sample Order 97",
            "phone": "0123456789",
            "price": "485",
            "total": 0,
            "date": "03/4/20",
            "uid": "1675303448945",
            "orderno": "97"
        },
        {
            "email": "email@sample.com",
            "items": "98",
            "name": "Sample",
            "order": "Sample Order 98",
            "phone": "0123456789",
            "price": "490",
            "total": 0,
            "date": "03/4/20",
            "uid": "1675303448945",
            "orderno": "98"
        },
        {
            "email": "email@sample.com",
            "items": "99",
            "name": "Sample",
            "order": "Sample Order 99",
            "phone": "0123456789",
            "price": "495",
            "total": 0,
            "date": "03/4/20",
            "uid": "1675303448945",
            "orderno": "99"
        },
        {
            "email": "email@sample.com",
            "items": "100",
            "name": "Sample",
            "order": "Sample Order 100",
            "phone": "0123456789",
            "price": "500",
            "total": 0,
            "date": "03/4/20",
            "uid": "1675303448945",
            "orderno": "100"
        }
    ]
}